trip/__init__.py
trip/admin.py
trip/apps.py
trip/forms.py
trip/models.py
trip/tests.py
trip/urls.py
trip/views.py
trip/api/urls.py
trip/api/views.py
trip/api/__pycache__/urls.cpython-310.pyc
trip/api/__pycache__/views.cpython-310.pyc
trip/migrations/0001_initial.py
trip/migrations/0002_trip_description.py
trip/migrations/0003_alter_trip_is_lock.py
trip/migrations/0004_alter_trip_is_lock.py
trip/migrations/0005_auto_20221211_1512.py
trip/migrations/0006_alter_tripemp_is_update.py
trip/migrations/0007_auto_20230131_1300.py
trip/migrations/0008_alter_trip_status.py
trip/migrations/0009_alter_trip_status.py
trip/migrations/0010_auto_20230201_2007.py
trip/migrations/__init__.py
trip/migrations/__pycache__/0001_initial.cpython-310.pyc
trip/migrations/__pycache__/0002_trip_description.cpython-310.pyc
trip/migrations/__pycache__/0003_alter_trip_is_lock.cpython-310.pyc
trip/migrations/__pycache__/0004_alter_trip_is_lock.cpython-310.pyc
trip/migrations/__pycache__/0005_auto_20221211_1512.cpython-310.pyc
trip/migrations/__pycache__/0006_alter_tripemp_is_update.cpython-310.pyc
trip/migrations/__pycache__/0007_auto_20230131_1300.cpython-310.pyc
trip/migrations/__pycache__/0008_alter_trip_status.cpython-310.pyc
trip/migrations/__pycache__/0009_alter_trip_status.cpython-310.pyc
trip/migrations/__pycache__/0010_auto_20230201_2007.cpython-310.pyc
trip/migrations/__pycache__/__init__.cpython-310.pyc
trip/templates/trip/dash.html
trip/templates/trip/detail.html
trip/templates/trip/emp_trip.js
trip/templates/trip/form.html
trip/templates/trip/list.html
trip/templates/trip/sumary.html
trip/templates/trip/tot_trip.js
trip/templates/trip_comp/delete_modal.html
trip/views/__init__.py
trip/views/m_trip.py
trip/views/v_trip.py
trip/views/__pycache__/__init__.cpython-310.pyc
trip/views/__pycache__/m_trip.cpython-310.pyc
trip/views/__pycache__/v_trip.cpython-310.pyc
django_ipghrms_trip-1.0.dist-info/LICENSE
django_ipghrms_trip-1.0.dist-info/METADATA
django_ipghrms_trip-1.0.dist-info/WHEEL
django_ipghrms_trip-1.0.dist-info/top_level.txt
django_ipghrms_trip-1.0.dist-info/RECORD
